github_projectv2/__init__.py
github_projectv2/base.py
github_projectv2/comment.py
github_projectv2/field.py
github_projectv2/item.py
github_projectv2/label.py
github_projectv2/milestone.py
github_projectv2/option.py
github_projectv2/organization.py
github_projectv2/project.py
github_projectv2/queries/partial/draftissue_item.graphql
github_projectv2/queries/partial/fields.graphql
github_projectv2/queries/partial/issue-timeline-events.graphql
github_projectv2/queries/partial/issue_item.graphql
github_projectv2/queries/partial/issue_item_slim.graphql
github_projectv2/queries/partial/item-project-node-id.graphql
github_projectv2/queries/partial/milestone.graphql
github_projectv2/queries/partial/repository.graphql
github_projectv2/queries/partial/timeline-events/added-to-project.graphql
github_projectv2/queries/partial/timeline-events/assigned.graphql
github_projectv2/queries/partial/timeline-events/closed.graphql
github_projectv2/queries/partial/timeline-events/comment-deleted.graphql
github_projectv2/queries/partial/timeline-events/cross-referenced.graphql
github_projectv2/queries/partial/timeline-events/demilestoned.graphql
github_projectv2/queries/partial/timeline-events/issue-comment.graphql
github_projectv2/queries/partial/timeline-events/issue-type-added.graphql
github_projectv2/queries/partial/timeline-events/issue-type-changed.graphql
github_projectv2/queries/partial/timeline-events/issue-type-removed.graphql
github_projectv2/queries/partial/timeline-events/labeled.graphql
github_projectv2/queries/partial/timeline-events/locked.graphql
github_projectv2/queries/partial/timeline-events/marked-as-duplicate.graphql
github_projectv2/queries/partial/timeline-events/mentioned.graphql
github_projectv2/queries/partial/timeline-events/milestoned.graphql
github_projectv2/queries/partial/timeline-events/moved-columns-in-project.graphql
github_projectv2/queries/partial/timeline-events/parent-issue-added.graphql
github_projectv2/queries/partial/timeline-events/pinned.graphql
github_projectv2-0.7.31.dist-info/LICENSE
github_projectv2-0.7.31.dist-info/METADATA
github_projectv2-0.7.31.dist-info/WHEEL
github_projectv2-0.7.31.dist-info/RECORD
