Metadata-Version: 2.3
Name: github-projectv2
Version: 0.7.31
Summary: 
Author: Chris Cornutt
Author-email: enygma@github.com
Requires-Python: >=3.10,<4.0
Classifier: Programming Language :: Python :: 3
Classifier: Programming Language :: Python :: 3.10
Classifier: Programming Language :: Python :: 3.11
Classifier: Programming Language :: Python :: 3.12
Classifier: Programming Language :: Python :: 3.13
